octadocs_adr/__init__.py
octadocs_adr/facets/__init__.py
octadocs_adr/facets/adr_list.py
octadocs_adr/facets/default.py
octadocs_adr/facets/link.py
octadocs_adr/facets/sidebar.py
octadocs_adr/facets/status.py
octadocs_adr/facets/status_class.py
octadocs_adr/macros.py
octadocs_adr/plugin.py
octadocs_adr/templates/octadocs-decisions/adr-list.html
octadocs_adr/templates/octadocs-decisions/adr.html
octadocs_adr/yaml/ctx.yaml
octadocs_adr/yaml/octadocs-adr.yaml
octadocs_adr-0.1.1.dist-info/entry_points.txt
octadocs_adr-0.1.1.dist-info/WHEEL
octadocs_adr-0.1.1.dist-info/METADATA
octadocs_adr-0.1.1.dist-info/RECORD
