Metadata-Version: 2.1
Name: octadocs-adr
Version: 0.1.1
Summary: A blueprint for Architecture Decision Record in Octadocs - the smart documentation environment.
Author: Anatoly Scherbakov
Author-email: talk@yeti.sh
Requires-Python: >=3.8,<3.10
Classifier: Programming Language :: Python :: 3
Classifier: Programming Language :: Python :: 3.8
Classifier: Programming Language :: Python :: 3.9
Requires-Dist: dominate (>=2.6.0,<3.0.0)
